{
  "Вес:1000.0 | Тип:Мука | Упаковка:Банка|plan:mid|all": {
    "positive": [
      {
        "topic": "качество муки",
        "percent": 45.0
      },
      {
        "topic": "вкус и аромат",
        "percent": 40.0
      },
      {
        "topic": "свежесть продукта",
        "percent": 30.0
      },
      {
        "topic": "упаковка и доставка",
        "percent": 15.0
      },
      {
        "topic": "подходит для диет и выпечки",
        "percent": 10.0
      }
    ],
    "negative": [
      {
        "topic": "качество и свежесть ухудшились",
        "percent": 25.0
      },
      {
        "topic": "неприятный запах и вкус (горечь, нутовый, химический)",
        "percent": 20.0
      },
      {
        "topic": "крупный или неоднородный помол",
        "percent": 15.0
      },
      {
        "topic": "проблемы с упаковкой (повреждения, просыпание)",
        "percent": 10.0
      },
      {
        "topic": "наличие посторонних примесей (личинки, комки)",
        "percent": 10.0
      },
      {
        "topic": "завышенная цена",
        "percent": 5.0
      }
    ],
    "improvements": [
      "Обеспечить стабильное качество и свежесть муки, избегать просрочки и ухудшения вкуса.",
      "Улучшить контроль помола для получения однородной и подходящей по размеру муки.",
      "Улучшить упаковку для предотвращения повреждений и просыпания муки при транспортировке.",
      "Проводить строгий контроль на отсутствие посторонних примесей и насекомых.",
      "Работать над устранением неприятных запахов и горечи, чтобы вкус соответствовал ожиданиям миндальной муки."
    ],
    "summary": "Большинство покупателей отмечают высокое качество, вкус и свежесть муки, а также удобную упаковку и быструю доставку. Однако значительная часть отзывов указывает на ухудшение качества, наличие неприятных запахов и вкусов, крупный помол и проблемы с упаковкой. Для повышения конкурентоспособности необходимо стабилизировать качество продукта, улучшить упаковку и контроль производства."
  }
}